{"ongoing_trials": {}, "hyperparameters": {"space": [{"class_name": "Choice", "config": {"name": "num_units", "default": 16, "conditions": [], "values": [16, 32], "ordered": true}}, {"class_name": "Choice", "config": {"name": "optimizer", "default": "adam", "conditions": [], "values": ["adam", "sgd"], "ordered": false}}], "values": {"num_units": 16, "optimizer": "adam"}}, "start_order": ["0", "1", "2", "3"], "end_order": ["0", "1", "2", "3"], "run_times": {"0": 1, "1": 1, "2": 1, "3": 1}, "retry_queue": [], "seed": 3697, "seed_state": 3711, "tried_so_far": ["555075cfb3138f9bbe642070330310e3", "c16bd823403b73b2478f601ea22251a1", "b48627a644480d0253d6db24b7636168", "cd55d83b0d339a2999db482d63dd90c5"], "id_to_hash": {"0": "c16bd823403b73b2478f601ea22251a1", "1": "b48627a644480d0253d6db24b7636168", "2": "cd55d83b0d339a2999db482d63dd90c5", "3": "555075cfb3138f9bbe642070330310e3"}, "display": {"search_start": "2024-06-26T20:18:23.534162", "trial_start": {"0": "2024-06-26T20:18:23.534162", "1": "2024-06-26T20:22:26.784787", "2": "2024-06-26T20:26:23.413451", "3": "2024-06-26T20:30:19.206318"}, "trial_number": {"0": 1, "1": 2, "2": 3, "3": 4}}}