{"trial_id": "1", "hyperparameters": {"space": [{"class_name": "Choice", "config": {"name": "num_units", "default": 16, "conditions": [], "values": [16, 32], "ordered": true}}, {"class_name": "Choice", "config": {"name": "optimizer", "default": "adam", "conditions": [], "values": ["adam", "sgd"], "ordered": false}}], "values": {"num_units": 16, "optimizer": "sgd"}}, "metrics": {"metrics": {"loss": {"direction": "min", "observations": [{"value": [0.22207393745581308], "step": 45}]}, "accuracy": {"direction": "max", "observations": [{"value": [0.9123422106107076], "step": 45}]}, "val_loss": {"direction": "min", "observations": [{"value": [0.23010128736495972], "step": 45}]}, "val_accuracy": {"direction": "max", "observations": [{"value": [0.9161993662516276], "step": 45}]}}}, "score": 0.9161993662516276, "best_step": 45, "status": "COMPLETED", "message": null}